cmdtube/__init__.py
cmdtube/cmdtube.py
cmdtube/functions/__init__.py
cmdtube/functions/download.py
cmdtube/functions/info.py
cmdtube/functions/search.py
cmdtube/functions/transcript.py
cmdtube/functions/watch.py
cmdtube-0.0.4.dist-info/LICENSE
cmdtube-0.0.4.dist-info/METADATA
cmdtube-0.0.4.dist-info/WHEEL
cmdtube-0.0.4.dist-info/top_level.txt
cmdtube-0.0.4.dist-info/RECORD
