Metadata-Version: 2.1
Name: cmdtube
Version: 0.0.4
Summary: A command-line interface for programmers who watch YouTube tutorials
Home-page: https://github.com/Samuel-HSSP/cmdtube
Author: Samuel Ogunleke
Author-email: Samuel Ogunleke <samuelayomidehssp@gmail.com>
Project-URL: Homepage, https://github.com/Samuel-HSSP/cmdtube
Project-URL: Issues, https://github.com/Samuel-HSSP/cmdtube/issues
Classifier: Programming Language :: Python :: 3
Classifier: License :: OSI Approved :: MIT License
Classifier: Operating System :: OS Independent
Requires-Python: >=3.8
License-File: LICENSE
